{
  "version": 3,
  "cmakeMinimumRequired": {
    "major": 3,
    "minor": 21,
    "patch": 0
  },
  "configurePresets": [
    {
      "name": "windows-nmake-release",
      "displayName": "Windows NMake Release Production",
      "description": "Production profile with DEFLATE reader/writer and image support enabled through default vcpkg features.",
      "generator": "NMake Makefiles",
      "binaryDir": "${sourceDir}/build/windows-nmake-release",
      "toolchainFile": "$env{VCPKG_ROOT}/scripts/buildsystems/vcpkg.cmake",
      "cacheVariables": {
        "CMAKE_BUILD_TYPE": "Release",
        "FASTXLSX_BUILD_TESTS": "ON",
        "FASTXLSX_BUILD_EXAMPLES": "OFF",
        "FASTXLSX_ENABLE_MINIZIP_NG": "ON",
        "FASTXLSX_ENABLE_DIRECT_ZLIB_PROFILING": "OFF",
        "FASTXLSX_ENABLE_PORTABLE_CRC_PROFILING": "OFF",
        "FASTXLSX_ENABLE_IMAGES": "ON"
      }
    },
    {
      "name": "windows-nmake-release-vcpkg",
      "displayName": "Windows NMake Release Production Compatibility",
      "description": "Compatibility alias for the production vcpkg-backed NMake Release profile.",
      "inherits": "windows-nmake-release",
      "binaryDir": "${sourceDir}/build/windows-nmake-release-vcpkg"
    },
    {
      "name": "windows-nmake-release-minizip",
      "displayName": "Windows NMake Release Production Compatibility (minizip)",
      "description": "Compatibility alias retained for existing scripts; production already enables minizip-ng.",
      "inherits": "windows-nmake-release",
      "binaryDir": "${sourceDir}/build/windows-nmake-release-minizip"
    },
    {
      "name": "windows-nmake-release-stored",
      "displayName": "Windows NMake Release Stored Bootstrap",
      "description": "Dependency-light stored ZIP bootstrap profile with images enabled and DEFLATE disabled.",
      "generator": "NMake Makefiles",
      "binaryDir": "${sourceDir}/build/windows-nmake-release-stored",
      "toolchainFile": "$env{VCPKG_ROOT}/scripts/buildsystems/vcpkg.cmake",
      "cacheVariables": {
        "CMAKE_BUILD_TYPE": "Release",
        "FASTXLSX_BUILD_TESTS": "ON",
        "FASTXLSX_BUILD_EXAMPLES": "OFF",
        "FASTXLSX_ENABLE_MINIZIP_NG": "OFF",
        "FASTXLSX_ENABLE_DIRECT_ZLIB_PROFILING": "OFF",
        "FASTXLSX_ENABLE_PORTABLE_CRC_PROFILING": "OFF",
        "FASTXLSX_ENABLE_IMAGES": "ON",
        "VCPKG_MANIFEST_NO_DEFAULT_FEATURES": "ON",
        "VCPKG_MANIFEST_FEATURES": "images"
      }
    },
    {
      "name": "windows-nmake-release-no-images",
      "displayName": "Windows NMake Release without Images",
      "description": "Production DEFLATE profile without stb/image support; builds the library and public disabled-feature stubs.",
      "generator": "NMake Makefiles",
      "binaryDir": "${sourceDir}/build/windows-nmake-release-no-images",
      "toolchainFile": "$env{VCPKG_ROOT}/scripts/buildsystems/vcpkg.cmake",
      "cacheVariables": {
        "CMAKE_BUILD_TYPE": "Release",
        "FASTXLSX_BUILD_TESTS": "OFF",
        "FASTXLSX_BUILD_EXAMPLES": "ON",
        "FASTXLSX_BUILD_FEATURE_SMOKES": "ON",
        "FASTXLSX_ENABLE_MINIZIP_NG": "ON",
        "FASTXLSX_ENABLE_DIRECT_ZLIB_PROFILING": "OFF",
        "FASTXLSX_ENABLE_PORTABLE_CRC_PROFILING": "OFF",
        "FASTXLSX_ENABLE_IMAGES": "OFF",
        "VCPKG_MANIFEST_NO_DEFAULT_FEATURES": "ON",
        "VCPKG_MANIFEST_FEATURES": "runtime-minizip"
      }
    },
    {
      "name": "windows-nmake-release-benchmark",
      "displayName": "Windows NMake Release Benchmark Production",
      "description": "Manual benchmarks with the production DEFLATE and image feature profile.",
      "generator": "NMake Makefiles",
      "binaryDir": "${sourceDir}/build/windows-nmake-release-benchmark",
      "toolchainFile": "$env{VCPKG_ROOT}/scripts/buildsystems/vcpkg.cmake",
      "cacheVariables": {
        "CMAKE_BUILD_TYPE": "Release",
        "FASTXLSX_BUILD_TESTS": "OFF",
        "FASTXLSX_BUILD_EXAMPLES": "OFF",
        "FASTXLSX_BUILD_BENCHMARKS": "ON",
        "FASTXLSX_ENABLE_MINIZIP_NG": "ON",
        "FASTXLSX_ENABLE_DIRECT_ZLIB_PROFILING": "ON",
        "FASTXLSX_ENABLE_PORTABLE_CRC_PROFILING": "OFF",
        "FASTXLSX_ENABLE_IMAGES": "ON"
      }
    },
    {
      "name": "windows-nmake-release-benchmark-minizip",
      "displayName": "Windows NMake Release Benchmark Compatibility (minizip)",
      "description": "Compatibility alias retained for existing benchmark scripts.",
      "inherits": "windows-nmake-release-benchmark",
      "binaryDir": "${sourceDir}/build/windows-nmake-release-benchmark-minizip"
    },
    {
      "name": "windows-nmake-release-reference-benchmark",
      "displayName": "Windows NMake Release Reference Benchmarks",
      "description": "Opt-in third-party XLSX writer reference benchmark adapters.",
      "generator": "NMake Makefiles",
      "binaryDir": "${sourceDir}/build/windows-nmake-release-reference-benchmark",
      "toolchainFile": "$env{VCPKG_ROOT}/scripts/buildsystems/vcpkg.cmake",
      "cacheVariables": {
        "CMAKE_BUILD_TYPE": "Release",
        "FASTXLSX_BUILD_TESTS": "OFF",
        "FASTXLSX_BUILD_EXAMPLES": "OFF",
        "FASTXLSX_BUILD_BENCHMARKS": "ON",
        "FASTXLSX_BUILD_REFERENCE_BENCHMARKS": "ON",
        "FASTXLSX_ENABLE_MINIZIP_NG": "ON",
        "FASTXLSX_ENABLE_DIRECT_ZLIB_PROFILING": "ON",
        "FASTXLSX_ENABLE_PORTABLE_CRC_PROFILING": "OFF",
        "FASTXLSX_ENABLE_IMAGES": "ON",
        "VCPKG_MANIFEST_FEATURES": "reference-benchmarks"
      }
    },
    {
      "name": "windows-nmake-release-direct-zlib-profile",
      "displayName": "Windows NMake Release Direct-zlib Profiling",
      "description": "Opt-in internal direct-zlib profiling engine with focused tests and manual benchmarks.",
      "generator": "NMake Makefiles",
      "binaryDir": "${sourceDir}/build/windows-nmake-zlib-profile",
      "toolchainFile": "$env{VCPKG_ROOT}/scripts/buildsystems/vcpkg.cmake",
      "cacheVariables": {
        "CMAKE_BUILD_TYPE": "Release",
        "FASTXLSX_BUILD_TESTS": "ON",
        "FASTXLSX_BUILD_EXAMPLES": "OFF",
        "FASTXLSX_BUILD_BENCHMARKS": "ON",
        "FASTXLSX_ENABLE_MINIZIP_NG": "ON",
        "FASTXLSX_ENABLE_DIRECT_ZLIB_PROFILING": "ON",
        "FASTXLSX_ENABLE_PORTABLE_CRC_PROFILING": "OFF",
        "FASTXLSX_ENABLE_IMAGES": "ON"
      }
    },
    {
      "name": "windows-nmake-release-patch-crc-minizip-profile",
      "displayName": "Windows NMake Release Patch CRC Minizip Profile",
      "description": "Internal Patch benchmark profile using minizip-ng CRC32 without direct-zlib profiling code.",
      "generator": "NMake Makefiles",
      "binaryDir": "${sourceDir}/build/windows-nmake-crc-minizip-profile",
      "toolchainFile": "$env{VCPKG_ROOT}/scripts/buildsystems/vcpkg.cmake",
      "cacheVariables": {
        "CMAKE_BUILD_TYPE": "Release",
        "FASTXLSX_BUILD_TESTS": "OFF",
        "FASTXLSX_BUILD_EXAMPLES": "OFF",
        "FASTXLSX_BUILD_BENCHMARKS": "ON",
        "FASTXLSX_ENABLE_MINIZIP_NG": "ON",
        "FASTXLSX_ENABLE_DIRECT_ZLIB_PROFILING": "OFF",
        "FASTXLSX_ENABLE_PORTABLE_CRC_PROFILING": "OFF",
        "FASTXLSX_ENABLE_IMAGES": "ON"
      }
    },
    {
      "name": "windows-nmake-release-patch-crc-portable-profile",
      "displayName": "Windows NMake Release Patch CRC Portable Profile",
      "description": "Internal Patch A/B benchmark profile forcing the portable CRC32 fallback with the same minizip-ng package backend.",
      "inherits": "windows-nmake-release-patch-crc-minizip-profile",
      "binaryDir": "${sourceDir}/build/windows-nmake-crc-portable-profile",
      "cacheVariables": {
        "FASTXLSX_ENABLE_PORTABLE_CRC_PROFILING": "ON"
      }
    }
  ],
  "buildPresets": [
    { "name": "windows-nmake-release", "configurePreset": "windows-nmake-release" },
    { "name": "windows-nmake-release-vcpkg", "configurePreset": "windows-nmake-release-vcpkg" },
    { "name": "windows-nmake-release-minizip", "configurePreset": "windows-nmake-release-minizip" },
    { "name": "windows-nmake-release-stored", "configurePreset": "windows-nmake-release-stored" },
    { "name": "windows-nmake-release-no-images", "configurePreset": "windows-nmake-release-no-images" },
    { "name": "windows-nmake-release-benchmark", "configurePreset": "windows-nmake-release-benchmark" },
    { "name": "windows-nmake-release-benchmark-minizip", "configurePreset": "windows-nmake-release-benchmark-minizip" },
    { "name": "windows-nmake-release-reference-benchmark", "configurePreset": "windows-nmake-release-reference-benchmark" },
    { "name": "windows-nmake-release-direct-zlib-profile", "configurePreset": "windows-nmake-release-direct-zlib-profile" },
    { "name": "windows-nmake-release-patch-crc-minizip-profile", "configurePreset": "windows-nmake-release-patch-crc-minizip-profile" },
    { "name": "windows-nmake-release-patch-crc-portable-profile", "configurePreset": "windows-nmake-release-patch-crc-portable-profile" }
  ],
  "testPresets": [
    {
      "name": "windows-nmake-release",
      "configurePreset": "windows-nmake-release",
      "output": { "outputOnFailure": true },
      "execution": { "noTestsAction": "error", "timeout": 60 }
    },
    {
      "name": "windows-nmake-release-vcpkg",
      "configurePreset": "windows-nmake-release-vcpkg",
      "output": { "outputOnFailure": true },
      "execution": { "noTestsAction": "error", "timeout": 60 }
    },
    {
      "name": "windows-nmake-release-minizip",
      "configurePreset": "windows-nmake-release-minizip",
      "output": { "outputOnFailure": true },
      "execution": { "noTestsAction": "error", "timeout": 60 }
    },
    {
      "name": "windows-nmake-release-stored",
      "configurePreset": "windows-nmake-release-stored",
      "output": { "outputOnFailure": true },
      "execution": { "noTestsAction": "error", "timeout": 60 }
    },
    {
      "name": "windows-nmake-release-direct-zlib-profile",
      "configurePreset": "windows-nmake-release-direct-zlib-profile",
      "output": { "outputOnFailure": true },
      "execution": { "noTestsAction": "error", "timeout": 60 }
    }
  ]
}
